fractal_converters_tools/__init__.py
fractal_converters_tools/_grid_utils.py
fractal_converters_tools/_microplate_utils.py
fractal_converters_tools/_omezarr_image_writers.py
fractal_converters_tools/_omezarr_plate_writers.py
fractal_converters_tools/_pkl_utils.py
fractal_converters_tools/_stitching.py
fractal_converters_tools/_task_common_models.py
fractal_converters_tools/_task_compute_tools.py
fractal_converters_tools/_task_init_tools.py
fractal_converters_tools/_tile.py
fractal_converters_tools/_tiled_image.py
fractal_converters_tools/py.typed
fractal_converters_tools-0.6.1.dist-info/METADATA
fractal_converters_tools-0.6.1.dist-info/WHEEL
fractal_converters_tools-0.6.1.dist-info/licenses/LICENSE
fractal_converters_tools-0.6.1.dist-info/RECORD
